pdchaoscli/__init__.py
pdchaoscli/__main__.py
pdchaoscli/cli.py
pdchaoscli/event.py
pdchaoscli/loader.py
pdchaoscli/logging.py
pdchaoscli/settings.py
pdchaoscli/api/__init__.py
pdchaoscli/api/applications.py
pdchaoscli/api/attacks.py
pdchaoscli/api/endpoints.py
pdchaoscli/api/scenarios.py
pdchaoscli/api/session.py
pdchaoscli/application/__init__.py
pdchaoscli/application/actions.py
pdchaoscli/experiment/__init__.py
pdchaoscli/experiment/activity.py
pdchaoscli/experiment/builder.py
proofdock_chaos_cli-0.0.8.dist-info/METADATA
proofdock_chaos_cli-0.0.8.dist-info/WHEEL
proofdock_chaos_cli-0.0.8.dist-info/entry_points.txt
proofdock_chaos_cli-0.0.8.dist-info/top_level.txt
proofdock_chaos_cli-0.0.8.dist-info/RECORD
