Metadata-Version: 2.1
Name: proofdock-chaos-cli
Version: 0.0.8
Summary: Chaos command line tool for the Proofdock Chaos Platform
Home-page: https://proofdock.io
Author: Proofdock
Author-email: hello@proofdock.io
License: Apache License Version 2.0
Project-URL: Documentation, https://docs.proofdock.io/
Project-URL: Support, https://github.com/proofdock/chaos-support
Platform: UNKNOWN
Classifier: Intended Audience :: Developers
Classifier: License :: Freely Distributable
Classifier: Operating System :: OS Independent
Classifier: License :: OSI Approved :: Apache Software License
Classifier: Programming Language :: Python
Classifier: Programming Language :: Python :: 3
Classifier: Programming Language :: Python :: 3.5
Classifier: Programming Language :: Python :: 3.6
Classifier: Programming Language :: Python :: 3.7
Classifier: Programming Language :: Python :: 3.8
Classifier: Programming Language :: Python :: Implementation
Classifier: Programming Language :: Python :: Implementation :: CPython
Requires-Python: >=3.5.*
Requires-Dist: click (==7.1.2)
Requires-Dist: chaostoolkit-lib (==1.15.0)
